{
    "demoInfo": {
        "fileName": "1-44d6f173-c621-4480-b9f1-a4640dcb3262.dem",
        "mapName": "de_inferno",
        "date": "2024-12-05 18:47:25",
        "aceKills": 0,
        "quadKills": 3,
        "multiKills": 0
    },
    "aceKills": [],
    "quadKills": [
        {
            "roundNumber": 4,
            "player": "Anthonydnise",
            "killCount": 4,
            "duration_in_ticks": 4690,
            "kills": [
                {
                    "attacker": {
                        "name": "Anthonydnise",
                        "steam64id": "76561198025966241",
                        "team": "CT",
                        "position": {
                            "x": 1360.294921875,
                            "y": 631.153564453125,
                            "z": 128.8722686767578
                        },
                        "viewAngles": {
                            "pitch": 6.9673919677734375,
                            "yaw": -154.31500244140625
                        }
                    },
                    "victim": {
                        "name": "alu_ese",
                        "steam64id": "76561199081876667",
                        "team": "TERRORIST",
                        "position": {
                            "x": 787.3805541992188,
                            "y": 350.2754211425781,
                            "z": 94.38526916503906
                        }
                    },
                    "killDetails": {
                        "tick": 26707,
                        "weapon": "m4a1_silencer",
                        "penetrationKill": false,
                        "headshot": false,
                        "noscope": false,
                        "thrusmoke": false,
                        "distance_to_enemy": 16.223588943481445,
                        "ticks_since_last_kill": 0,
                        "distance_moved_since_last_kill": 0.0
                    }
                },
                {
                    "attacker": {
                        "name": "Anthonydnise",
                        "steam64id": "76561198025966241",
                        "team": "CT",
                        "position": {
                            "x": 1467.6390380859375,
                            "y": 1233.546630859375,
                            "z": 175.95155334472656
                        },
                        "viewAngles": {
                            "pitch": 3.03497314453125,
                            "yaw": -90.845947265625
                        }
                    },
                    "victim": {
                        "name": "NothingSpcl",
                        "steam64id": "76561198071754761",
                        "team": "TERRORIST",
                        "position": {
                            "x": 1460.880126953125,
                            "y": 241.26376342773438,
                            "z": 128.03125
                        }
                    },
                    "killDetails": {
                        "tick": 30074,
                        "weapon": "m4a1_silencer",
                        "penetrationKill": false,
                        "headshot": false,
                        "noscope": false,
                        "thrusmoke": false,
                        "distance_to_enemy": 25.533170700073242,
                        "ticks_since_last_kill": 3367,
                        "distance_moved_since_last_kill": 613.6909847669914
                    },
                    "assist": {
                        "name": "Sawvak",
                        "steam64id": "76561199213160471",
                        "team": "CT",
                        "flashAssist": false
                    }
                },
                {
                    "attacker": {
                        "name": "Anthonydnise",
                        "steam64id": "76561198025966241",
                        "team": "CT",
                        "position": {
                            "x": 1360.7861328125,
                            "y": 1196.021484375,
                            "z": 181.03125
                        },
                        "viewAngles": {
                            "pitch": 4.244842529296875,
                            "yaw": -86.3909912109375
                        }
                    },
                    "victim": {
                        "name": "Shmeg1994",
                        "steam64id": "76561199745645831",
                        "team": "TERRORIST",
                        "position": {
                            "x": 1412.42041015625,
                            "y": 115.17243194580078,
                            "z": 132.03125
                        }
                    },
                    "killDetails": {
                        "tick": 31314,
                        "weapon": "m4a1_silencer",
                        "penetrationKill": false,
                        "headshot": false,
                        "noscope": false,
                        "thrusmoke": false,
                        "distance_to_enemy": 27.628334045410156,
                        "ticks_since_last_kill": 1240,
                        "distance_moved_since_last_kill": 113.36438286409715
                    },
                    "assist": {
                        "name": "Sawvak",
                        "steam64id": "76561199213160471",
                        "team": "CT",
                        "flashAssist": false
                    }
                },
                {
                    "attacker": {
                        "name": "Anthonydnise",
                        "steam64id": "76561198025966241",
                        "team": "CT",
                        "position": {
                            "x": 1436.8626708984375,
                            "y": 1196.2642822265625,
                            "z": 177.11805725097656
                        },
                        "viewAngles": {
                            "pitch": 5.9223175048828125,
                            "yaw": -95.16357421875
                        }
                    },
                    "victim": {
                        "name": "goldTable",
                        "steam64id": "76561199277037437",
                        "team": "TERRORIST",
                        "position": {
                            "x": 1322.031982421875,
                            "y": 142.16110229492188,
                            "z": 138.03125
                        }
                    },
                    "killDetails": {
                        "tick": 31397,
                        "weapon": "m4a1_silencer",
                        "penetrationKill": false,
                        "headshot": false,
                        "noscope": false,
                        "thrusmoke": false,
                        "distance_to_enemy": 27.041976928710938,
                        "ticks_since_last_kill": 83,
                        "distance_moved_since_last_kill": 76.1775011104252
                    }
                }
            ],
            "metadata": {
                "weapons_used": [
                    "m4a1_silencer"
                ],
                "headshots": 0,
                "wallbangs": 0,
                "radius_moved": 437.09751214863803,
                "victims_in_radius": 479.50210369688034,
                "total_distance_moved": 803.2328687415137
            }
        },
        {
            "roundNumber": 10,
            "player": "Buckysr",
            "killCount": 4,
            "duration_in_ticks": 3626,
            "kills": [
                {
                    "attacker": {
                        "name": "Buckysr",
                        "steam64id": "76561198088022403",
                        "team": "CT",
                        "position": {
                            "x": 755.6287841796875,
                            "y": 22.14580726623535,
                            "z": 85.15966796875
                        },
                        "viewAngles": {
                            "pitch": -5.14813232421875,
                            "yaw": -170.41683959960938
                        }
                    },
                    "victim": {
                        "name": "woku",
                        "steam64id": "76561199414987806",
                        "team": "TERRORIST",
                        "position": {
                            "x": -405.06414794921875,
                            "y": -201.7318115234375,
                            "z": 192.03125
                        }
                    },
                    "killDetails": {
                        "tick": 68167,
                        "weapon": "m4a1_silencer",
                        "penetrationKill": false,
                        "headshot": false,
                        "noscope": false,
                        "thrusmoke": false,
                        "distance_to_enemy": 30.299129486083984,
                        "ticks_since_last_kill": 0,
                        "distance_moved_since_last_kill": 0.0
                    }
                },
                {
                    "attacker": {
                        "name": "Buckysr",
                        "steam64id": "76561198088022403",
                        "team": "CT",
                        "position": {
                            "x": 280.35577392578125,
                            "y": 21.493152618408203,
                            "z": 66.03125
                        },
                        "viewAngles": {
                            "pitch": -4.910552978515625,
                            "yaw": -57.55668640136719
                        }
                    },
                    "victim": {
                        "name": "goldTable",
                        "steam64id": "76561199277037437",
                        "team": "TERRORIST",
                        "position": {
                            "x": 394.29052734375,
                            "y": -179.3609619140625,
                            "z": 110.03125
                        }
                    },
                    "killDetails": {
                        "tick": 69225,
                        "weapon": "m4a1_silencer",
                        "penetrationKill": false,
                        "headshot": false,
                        "noscope": false,
                        "thrusmoke": false,
                        "distance_to_enemy": 6.010201454162598,
                        "ticks_since_last_kill": 1058,
                        "distance_moved_since_last_kill": 475.6582350888989
                    }
                },
                {
                    "attacker": {
                        "name": "Buckysr",
                        "steam64id": "76561198088022403",
                        "team": "CT",
                        "position": {
                            "x": -612.1376953125,
                            "y": 724.6829223632812,
                            "z": -22.844482421875
                        },
                        "viewAngles": {
                            "pitch": -5.8344268798828125,
                            "yaw": 8.15289306640625
                        }
                    },
                    "victim": {
                        "name": "NothingSpcl",
                        "steam64id": "76561198071754761",
                        "team": "TERRORIST",
                        "position": {
                            "x": 55.47466278076172,
                            "y": 809.8939819335938,
                            "z": 80.03125
                        }
                    },
                    "killDetails": {
                        "tick": 71092,
                        "weapon": "m4a1_silencer",
                        "penetrationKill": false,
                        "headshot": false,
                        "noscope": false,
                        "thrusmoke": false,
                        "distance_to_enemy": 17.366975784301758,
                        "ticks_since_last_kill": 1867,
                        "distance_moved_since_last_kill": 1139.7014261289467
                    }
                },
                {
                    "attacker": {
                        "name": "Buckysr",
                        "steam64id": "76561198088022403",
                        "team": "CT",
                        "position": {
                            "x": 77.97412872314453,
                            "y": 893.3739013671875,
                            "z": 80.14175415039062
                        },
                        "viewAngles": {
                            "pitch": -1.0031890869140625,
                            "yaw": 74.15290832519531
                        }
                    },
                    "victim": {
                        "name": "alu_ese",
                        "steam64id": "76561199081876667",
                        "team": "TERRORIST",
                        "position": {
                            "x": 228.3349609375,
                            "y": 1350.3402099609375,
                            "z": 108.1719970703125
                        }
                    },
                    "killDetails": {
                        "tick": 71793,
                        "weapon": "usp_silencer",
                        "penetrationKill": false,
                        "headshot": false,
                        "noscope": false,
                        "thrusmoke": false,
                        "distance_to_enemy": 12.81178092956543,
                        "ticks_since_last_kill": 701,
                        "distance_moved_since_last_kill": 717.8559333142127
                    },
                    "assist": {
                        "name": "Kille-e",
                        "steam64id": "76561198139875934",
                        "team": "CT",
                        "flashAssist": false
                    }
                }
            ],
            "metadata": {
                "weapons_used": [
                    "m4a1_silencer",
                    "usp_silencer"
                ],
                "headshots": 0,
                "wallbangs": 0,
                "radius_moved": 803.3084370053016,
                "victims_in_radius": 919.7070778008978,
                "total_distance_moved": 2333.2155945320583
            }
        },
        {
            "roundNumber": 13,
            "player": "alu_ese",
            "killCount": 4,
            "duration_in_ticks": 1145,
            "kills": [
                {
                    "attacker": {
                        "name": "alu_ese",
                        "steam64id": "76561199081876667",
                        "team": "CT",
                        "position": {
                            "x": 793.5118408203125,
                            "y": 1933.83740234375,
                            "z": 136.6851348876953
                        },
                        "viewAngles": {
                            "pitch": 3.44970703125,
                            "yaw": 175.25631713867188
                        }
                    },
                    "victim": {
                        "name": "Buckysr",
                        "steam64id": "76561198088022403",
                        "team": "TERRORIST",
                        "position": {
                            "x": 344.8132019042969,
                            "y": 1969.962158203125,
                            "z": 136.26898193359375
                        }
                    },
                    "killDetails": {
                        "tick": 85494,
                        "weapon": "mp9",
                        "penetrationKill": false,
                        "headshot": true,
                        "noscope": false,
                        "thrusmoke": false,
                        "distance_to_enemy": 11.552020072937012,
                        "ticks_since_last_kill": 0,
                        "distance_moved_since_last_kill": 0.0
                    }
                },
                {
                    "attacker": {
                        "name": "alu_ese",
                        "steam64id": "76561199081876667",
                        "team": "CT",
                        "position": {
                            "x": 790.471923828125,
                            "y": 1938.1617431640625,
                            "z": 136.6851348876953
                        },
                        "viewAngles": {
                            "pitch": 7.814361572265625,
                            "yaw": 178.77639770507812
                        }
                    },
                    "victim": {
                        "name": "Kille-e",
                        "steam64id": "76561198139875934",
                        "team": "TERRORIST",
                        "position": {
                            "x": 292.4266052246094,
                            "y": 1896.0460205078125,
                            "z": 137.03125
                        }
                    },
                    "killDetails": {
                        "tick": 85535,
                        "weapon": "mp9",
                        "penetrationKill": false,
                        "headshot": false,
                        "noscope": false,
                        "thrusmoke": false,
                        "distance_to_enemy": 12.712512969970703,
                        "ticks_since_last_kill": 41,
                        "distance_moved_since_last_kill": 5.285926489236422
                    }
                },
                {
                    "attacker": {
                        "name": "alu_ese",
                        "steam64id": "76561199081876667",
                        "team": "CT",
                        "position": {
                            "x": 844.4612426757812,
                            "y": 2006.3817138671875,
                            "z": 136.03128051757812
                        },
                        "viewAngles": {
                            "pitch": 4.751922607421875,
                            "yaw": -161.93402099609375
                        }
                    },
                    "victim": {
                        "name": "AdAmA4",
                        "steam64id": "76561199045376655",
                        "team": "TERRORIST",
                        "position": {
                            "x": 326.16619873046875,
                            "y": 1821.911376953125,
                            "z": 125.98651885986328
                        }
                    },
                    "killDetails": {
                        "tick": 85742,
                        "weapon": "mp9",
                        "penetrationKill": false,
                        "headshot": true,
                        "noscope": false,
                        "thrusmoke": false,
                        "distance_to_enemy": 14.078021049499512,
                        "ticks_since_last_kill": 207,
                        "distance_moved_since_last_kill": 87.00137055188524
                    },
                    "assist": {
                        "name": "NothingSpcl",
                        "steam64id": "76561198071754761",
                        "team": "CT",
                        "flashAssist": false
                    }
                },
                {
                    "attacker": {
                        "name": "alu_ese",
                        "steam64id": "76561199081876667",
                        "team": "CT",
                        "position": {
                            "x": 400.7663269042969,
                            "y": 1784.706787109375,
                            "z": 134.03121948242188
                        },
                        "viewAngles": {
                            "pitch": 9.785736083984375,
                            "yaw": -102.76302337646484
                        }
                    },
                    "victim": {
                        "name": "Anthonydnise",
                        "steam64id": "76561198025966241",
                        "team": "TERRORIST",
                        "position": {
                            "x": 378.6026916503906,
                            "y": 1680.4364013671875,
                            "z": 134.03128051757812
                        }
                    },
                    "killDetails": {
                        "tick": 86639,
                        "weapon": "m4a1_silencer",
                        "penetrationKill": false,
                        "headshot": false,
                        "noscope": false,
                        "thrusmoke": false,
                        "distance_to_enemy": 2.7636237144470215,
                        "ticks_since_last_kill": 897,
                        "distance_moved_since_last_kill": 495.9928947864984
                    }
                }
            ],
            "metadata": {
                "weapons_used": [
                    "m4a1_silencer",
                    "mp9"
                ],
                "headshots": 2,
                "wallbangs": 0,
                "radius_moved": 333.3857144575872,
                "victims_in_radius": 167.30124400565649,
                "total_distance_moved": 588.2801918276201
            }
        }
    ],
    "multiKills": []
}